CHANGELOG.rst
LICENSE
mp_yearmonth/__init__.py
mp_yearmonth/yearmonth.py
mp_yearmonth-0.5.0.dist-info/LICENSE
mp_yearmonth-0.5.0.dist-info/METADATA
mp_yearmonth-0.5.0.dist-info/WHEEL
mp_yearmonth-0.5.0.dist-info/RECORD
