Metadata-Version: 2.1
Name: mp-yearmonth
Version: 0.5.0
Summary: A year-month datatype for Python.
Keywords: year,month,date,calendar
Author: Ramon Torres
Author-email: ramon@macropoetry.com
Requires-Python: >=3.7,<4.0
Classifier: Development Status :: 5 - Production/Stable
Classifier: Intended Audience :: Developers
Classifier: License :: OSI Approved :: MIT License
Classifier: Operating System :: OS Independent
Classifier: Programming Language :: Python
Classifier: Programming Language :: Python :: 3
Classifier: Programming Language :: Python :: 3.7
Classifier: Programming Language :: Python :: 3.8
Classifier: Programming Language :: Python :: 3.9
Classifier: Programming Language :: Python :: 3.10
Classifier: Programming Language :: Python :: 3.11
Classifier: Programming Language :: Python :: 3.12
Classifier: Typing :: Typed
Project-URL: homepage, https://github.com/raymondjavaxx/mp-yearmonth
Project-URL: repository, https://github.com/raymondjavaxx/mp-yearmonth
Project-URL: tracker, https://github.com/raymondjavaxx/mp-yearmonth/issues
